setup.py
aosong/__init__.py
aosong/am2315.py
aosong.egg-info/PKG-INFO
aosong.egg-info/SOURCES.txt
aosong.egg-info/dependency_links.txt
aosong.egg-info/requires.txt
aosong.egg-info/top_level.txt
tests/__init__.py
tests/am2315.py