Metadata-Version: 1.1
Name: aosong
Version: 0.0.2
Summary: AOSONG Sensors.
Home-page: http://sopwith.ismellsmoke.net/?p=104
Author: Matt Heitzenroder
Author-email: mheitzenroder@gmail.com
License: Apache-2.0
Platform: Linux
Classifier: Development Status :: 4 - Beta
Classifier: Environment :: Console
Classifier: Intended Audience :: Developers
Classifier: License :: OSI Approved :: Apache Software License
Classifier: Programming Language :: Python
Classifier: Programming Language :: Python :: 3
Classifier: Natural Language :: English
